<CsvDataTemplateObject Version="1.0"><Name>Yahoo Finance</Name><Description /><NumberOfLinesToSkip>0</NumberOfLinesToSkip><AllowComments>true</AllowComments><Comment>35</Comment><HasHeaderRecord>true</HasHeaderRecord><Delimiter>,</Delimiter><Quote>34</Quote><IgnoreQuotes>false</IgnoreQuotes><CsvDataColumnObjects><CsvDataColumnObject Version="1.0"><UseColumnName>true</UseColumnName><ColumnName>Symbol</ColumnName><ColumnIndex>0</ColumnIndex><ParameterValue /><FieldType>Symbol</FieldType><PreprocessingType>Preprocess</PreprocessingType><NewColumnName /><PreprocessingCode>value.split(".")[0];</PreprocessingCode></CsvDataColumnObject><CsvDataColumnObject Version="1.0"><UseColumnName>true</UseColumnName><ColumnName>Trade Date</ColumnName><ColumnIndex>0</ColumnIndex><ParameterValue>US</ParameterValue><FieldType>TransactionDateTime</FieldType><PreprocessingType>Preprocess</PreprocessingType><NewColumnName /><PreprocessingCode>value.slice(4, 6) + '/' + value.slice(6, 8) + '/' +value.slice(0, 4);</PreprocessingCode></CsvDataColumnObject><CsvDataColumnObject Version="1.0"><UseColumnName>true</UseColumnName><ColumnName>Purchase Price</ColumnName><ColumnIndex>0</ColumnIndex><ParameterValue /><FieldType>Price</FieldType><PreprocessingType>None</PreprocessingType><NewColumnName /><PreprocessingCode /></CsvDataColumnObject><CsvDataColumnObject Version="1.0"><UseColumnName>true</UseColumnName><ColumnName>Quantity</ColumnName><ColumnIndex>0</ColumnIndex><ParameterValue /><FieldType>Quantity</FieldType><PreprocessingType>None</PreprocessingType><NewColumnName /><PreprocessingCode /></CsvDataColumnObject><CsvDataColumnObject Version="1.0"><UseColumnName>true</UseColumnName><ColumnName>Comment</ColumnName><ColumnIndex>0</ColumnIndex><ParameterValue /><FieldType>Note</FieldType><PreprocessingType>None</PreprocessingType><NewColumnName /><PreprocessingCode /></CsvDataColumnObject><CsvDataColumnObject Version="1.0"><UseColumnName>true</UseColumnName><ColumnName>Current Price</ColumnName><ColumnIndex>0</ColumnIndex><ParameterValue /><FieldType>None</FieldType><PreprocessingType>None</PreprocessingType><NewColumnName /><PreprocessingCode /></CsvDataColumnObject><CsvDataColumnObject Version="1.0"><UseColumnName>false</UseColumnName><ColumnName /><ColumnIndex>0</ColumnIndex><ParameterValue /><FieldType>TransactionType</FieldType><PreprocessingType>GenerateNewColumn</PreprocessingType><NewColumnName>Transaction Type</NewColumnName><PreprocessingCode>'B';</PreprocessingCode></CsvDataColumnObject><CsvDataColumnObject Version="1.0"><UseColumnName>false</UseColumnName><ColumnName /><ColumnIndex>0</ColumnIndex><ParameterValue /><FieldType>BrokerageExpenses</FieldType><PreprocessingType>GenerateNewColumn</PreprocessingType><NewColumnName>Brokerage Expenses</NewColumnName><PreprocessingCode>'0';</PreprocessingCode></CsvDataColumnObject></CsvDataColumnObjects></CsvDataTemplateObject>
